pyomniunwarp/__init__.py
pyomniunwarp/example.py
pyomniunwarp/remap.py
pyomniunwarp/data/calib_results.txt
pyomniunwarp/data/example.jpg
pyomniunwarp-0.2.0.dist-info/LICENSE
pyomniunwarp-0.2.0.dist-info/METADATA
pyomniunwarp-0.2.0.dist-info/WHEEL
pyomniunwarp-0.2.0.dist-info/top_level.txt
pyomniunwarp-0.2.0.dist-info/RECORD
