Metadata-Version: 2.1
Name: pyomniunwarp
Version: 0.2.0
Summary: A simple tool for unwrapping 360 degrees omnidirectional images.
Home-page: https://github.com/KuanLi-LFI/omniunwarp
Author: Kuan Li
Author-email: kuan.li@lfi.ai
License: MIT
Classifier: License :: OSI Approved :: MIT License
Classifier: Programming Language :: Python
Classifier: Programming Language :: Python :: 3
Classifier: Programming Language :: Python :: 3.6
Classifier: Programming Language :: Python :: Implementation :: CPython
Classifier: Programming Language :: Python :: Implementation :: PyPy
Requires-Python: >=3.6.0
License-File: LICENSE
Requires-Dist: opencv-python
